DynamicHtml/DynamicGetter.py
DynamicHtml/__init__.py
DynamicHtml-1.0.3.dist-info/METADATA
DynamicHtml-1.0.3.dist-info/WHEEL
DynamicHtml-1.0.3.dist-info/top_level.txt
DynamicHtml-1.0.3.dist-info/RECORD
