Metadata-Version: 2.1
Name: DynamicHtml
Version: 1.0.3
Summary: An extremely simple library used for gathering html from dynamic webpages using Pyppeteer.
Home-page: https://github.com/commonkestrel/DynamicHtml
Author: Kestrel
License: MIT
Requires-Python: >= 3.4
Requires-Dist: pyppeteer
